[{"buyer": {"$binary": {"base64": "xt+zMrvITQCJTp+hF/Bg1Q==", "subType": "03"}}, "_id": {"$binary": {"base64": "Y770PVv0TVOXPye565oCEw==", "subType": "03"}}, "_class": "org.example.persistence.collections.PurchaseOrder", "uri": "e84ad49a-5868-422a-92eb-4549a1d003cb.pdf", "items": [{"description": "kickstarter", "quantity": {"$numberInt": "3"}, "price": {"$numberDouble": "23.916152794837863"}}, {"description": "poutine", "quantity": {"$numberInt": "12"}, "price": {"$numberDouble": "80.35159971437287"}}], "version": {"$numberInt": "8"}, "orderStatus": "CREATED", "seller": {"$binary": {"base64": "X6nYatYNTji2zGnBRuU1WA==", "subType": "03"}}}, {"buyer": {"$binary": {"base64": "RjFBw42VTA2sO0yXPH14Aw==", "subType": "03"}}, "_id": {"$binary": {"base64": "eLV0dXHhT0StaW1qVGBUVQ==", "subType": "03"}}, "_class": "org.example.persistence.collections.PurchaseOrder", "uri": "4b5b7c97-412a-48fd-a3e2-850335960836.pdf", "items": [{"description": "kogi", "quantity": {"$numberInt": "18"}, "price": {"$numberDouble": "74.73585085479657"}}, {"description": "occupy", "quantity": {"$numberInt": "9"}, "price": {"$numberDouble": "48.47013183232989"}}, {"description": "ugh", "quantity": {"$numberInt": "3"}, "price": {"$numberDouble": "108.08298695272956"}}, {"description": "readymade", "quantity": {"$numberInt": "9"}, "price": {"$numberDouble": "84.75789303555922"}}, {"description": "lo-fi", "quantity": {"$numberInt": "15"}, "price": {"$numberDouble": "57.97538373210484"}}, {"description": "chillwave", "quantity": {"$numberInt": "12"}, "price": {"$numberDouble": "121.6482363205512"}}, {"description": "plaid", "quantity": {"$numberInt": "7"}, "price": {"$numberDouble": "49.67596695490417"}}, {"description": "Wes Anderson", "quantity": {"$numberInt": "13"}, "price": {"$numberDouble": "94.26721857692596"}}, {"description": "Thundercats", "quantity": {"$numberInt": "1"}, "price": {"$numberDouble": "87.90472610350498"}}, {"description": "hammock", "quantity": {"$numberInt": "5"}, "price": {"$numberDouble": "107.07737991234237"}}], "version": {"$numberInt": "1"}, "orderStatus": "SAVED", "seller": {"$binary": {"base64": "BYAUjF6BQxatEI3VCGnZew==", "subType": "03"}}}, {"buyer": {"$binary": {"base64": "ke7B55BRSWyht+egLJvjBw==", "subType": "03"}}, "_id": {"$binary": {"base64": "gxJ2x4geQ+qv0mvr5CJihQ==", "subType": "03"}}, "_class": "org.example.persistence.collections.PurchaseOrder", "uri": "932a3dc5-d10d-4511-a471-79d79b824164.pdf", "items": [{"description": "sriracha", "quantity": {"$numberInt": "10"}, "price": {"$numberDouble": "98.8435295882413"}}, {"description": "gluten-free", "quantity": {"$numberInt": "9"}, "price": {"$numberDouble": "109.55995164226408"}}, {"description": "carry", "quantity": {"$numberInt": "19"}, "price": {"$numberDouble": "123.70855638127037"}}], "version": {"$numberInt": "5"}, "orderStatus": "APPROVED", "seller": {"$binary": {"base64": "sl2jTBg1SCKznpo0jH5DrA==", "subType": "03"}}}, {"buyer": {"$binary": {"base64": "ke7B55BRSWyht+egLJvjBw==", "subType": "03"}}, "_id": {"$binary": {"base64": "2xFZuZLnQheOEgpjRlt48A==", "subType": "03"}}, "_class": "org.example.persistence.collections.PurchaseOrder", "uri": "94ee2e4d-383d-44b5-abff-a52c0b548ca2.pdf", "items": [{"description": "heirloom", "quantity": {"$numberInt": "17"}, "price": {"$numberDouble": "73.39390519489731"}}, {"description": "lomo", "quantity": {"$numberInt": "7"}, "price": {"$numberDouble": "53.98887949727119"}}], "version": {"$numberInt": "5"}, "orderStatus": "REJECTED", "seller": {"$binary": {"base64": "7uhdUuk+R6StPbvlM8NXVw==", "subType": "03"}}}, {"buyer": {"$binary": {"base64": "IKFcS9F/QouukuifQOz7bA==", "subType": "03"}}, "_id": {"$binary": {"base64": "AZEFehP0T0ikmZZkvla3LQ==", "subType": "03"}}, "_class": "org.example.persistence.collections.PurchaseOrder", "uri": "7fc46676-c098-489a-a786-af568c1c2dcc.pdf", "items": [{"description": "scenester", "quantity": {"$numberInt": "8"}, "price": {"$numberDouble": "84.76182741906918"}}, {"description": "quinoa", "quantity": {"$numberInt": "10"}, "price": {"$numberDouble": "97.10459032702279"}}, {"description": "ugh", "quantity": {"$numberInt": "14"}, "price": {"$numberDouble": "17.003875407610423"}}, {"description": "flexitarian", "quantity": {"$numberInt": "7"}, "price": {"$numberDouble": "106.87666311701577"}}, {"description": "direct trade", "quantity": {"$numberInt": "19"}, "price": {"$numberDouble": "63.13356737626957"}}, {"description": "artisan", "quantity": {"$numberInt": "15"}, "price": {"$numberDouble": "100.12665578781538"}}, {"description": "swag", "quantity": {"$numberInt": "14"}, "price": {"$numberDouble": "118.3274208039563"}}, {"description": "farm-to-table", "quantity": {"$numberInt": "3"}, "price": {"$numberDouble": "30.812227231643263"}}, {"description": "microdosing", "quantity": {"$numberInt": "6"}, "price": {"$numberDouble": "32.81391736565428"}}, {"description": "umami", "quantity": {"$numberInt": "9"}, "price": {"$numberDouble": "56.77139825974039"}}], "version": {"$numberInt": "7"}, "orderStatus": "CREATED", "seller": {"$binary": {"base64": "cbC9UP2yQ4OPJyYk1ZWd6Q==", "subType": "03"}}}, {"buyer": {"$binary": {"base64": "xLpqDCrvS26gOS1zhp339g==", "subType": "03"}}, "_id": {"$binary": {"base64": "8HIDKn68QjaKQ+DgZZqKyQ==", "subType": "03"}}, "_class": "org.example.persistence.collections.PurchaseOrder", "uri": "4b06168d-2fea-406a-b163-f3f1679df82d.pdf", "items": [{"description": "try-hard", "quantity": {"$numberInt": "6"}, "price": {"$numberDouble": "33.52821395770734"}}, {"description": "portland", "quantity": {"$numberInt": "11"}, "price": {"$numberDouble": "103.90136552850994"}}, {"description": "you probably haven't heard of them", "quantity": {"$numberInt": "13"}, "price": {"$numberDouble": "108.7354053851214"}}, {"description": "paleo", "quantity": {"$numberInt": "12"}, "price": {"$numberDouble": "114.30257095602015"}}, {"description": "whatever", "quantity": {"$numberInt": "7"}, "price": {"$numberDouble": "108.94311670628882"}}, {"description": "pabst", "quantity": {"$numberInt": "20"}, "price": {"$numberDouble": "53.55028109194722"}}, {"description": "austin", "quantity": {"$numberInt": "1"}, "price": {"$numberDouble": "33.57507930697294"}}, {"description": "waistcoat", "quantity": {"$numberInt": "20"}, "price": {"$numberDouble": "117.15240041519547"}}, {"description": "normcore", "quantity": {"$numberInt": "5"}, "price": {"$numberDouble": "127.34876919681484"}}, {"description": "chillwave", "quantity": {"$numberInt": "8"}, "price": {"$numberDouble": "87.87093618285898"}}, {"description": "marfa", "quantity": {"$numberInt": "13"}, "price": {"$numberDouble": "55.91349990481911"}}, {"description": "3 wolf moon", "quantity": {"$numberInt": "2"}, "price": {"$numberDouble": "86.60454988142916"}}], "version": {"$numberInt": "2"}, "orderStatus": "SAVED", "seller": {"$binary": {"base64": "2Ekz5dbJRgS+v8ol2igUyA==", "subType": "03"}}}, {"buyer": {"$binary": {"base64": "X6nYatYNTji2zGnBRuU1WA==", "subType": "03"}}, "_id": {"$binary": {"base64": "F6LzA8IVRzuWbzjxPl/+vw==", "subType": "03"}}, "_class": "org.example.persistence.collections.PurchaseOrder", "uri": "738a697c-ae66-45ca-be61-b02a00f00b65.pdf", "items": [{"description": "paleo", "quantity": {"$numberInt": "14"}, "price": {"$numberDouble": "48.4228240436561"}}, {"description": "hoodie", "quantity": {"$numberInt": "2"}, "price": {"$numberDouble": "80.30181826805804"}}, {"description": "deep v", "quantity": {"$numberInt": "3"}, "price": {"$numberDouble": "75.49540667264789"}}], "version": {"$numberInt": "7"}, "orderStatus": "APPROVED", "seller": {"$binary": {"base64": "Rulzo7ZdQw2BVLDpqrV8lQ==", "subType": "03"}}}, {"buyer": {"$binary": {"base64": "r1iWXC3eSbyFKhvMl60WBQ==", "subType": "03"}}, "_id": {"$binary": {"base64": "hDGaEN6GQkewu7srGmxVKg==", "subType": "03"}}, "_class": "org.example.persistence.collections.PurchaseOrder", "uri": "7a06a19f-74cf-4ca5-be20-f5f130e24c2c.pdf", "items": [{"description": "gluten-free", "quantity": {"$numberInt": "4"}, "price": {"$numberDouble": "93.41980871589928"}}, {"description": "poutine", "quantity": {"$numberInt": "2"}, "price": {"$numberDouble": "124.338065632342"}}, {"description": "semiotics", "quantity": {"$numberInt": "8"}, "price": {"$numberDouble": "81.81902620621177"}}, {"description": "Yuccie", "quantity": {"$numberInt": "18"}, "price": {"$numberDouble": "29.04508586174719"}}, {"description": "freegan", "quantity": {"$numberInt": "9"}, "price": {"$numberDouble": "13.101261087804843"}}, {"description": "shoreditch", "quantity": {"$numberInt": "4"}, "price": {"$numberDouble": "88.4376305771823"}}, {"description": "chia", "quantity": {"$numberInt": "5"}, "price": {"$numberDouble": "116.36009545432687"}}, {"description": "tofu", "quantity": {"$numberInt": "20"}, "price": {"$numberDouble": "83.85420967367169"}}, {"description": "swag", "quantity": {"$numberInt": "3"}, "price": {"$numberDouble": "36.7940345714599"}}, {"description": "pour-over", "quantity": {"$numberInt": "13"}, "price": {"$numberDouble": "14.36351061105037"}}, {"description": "ennui", "quantity": {"$numberInt": "15"}, "price": {"$numberDouble": "127.19876512342199"}}], "version": {"$numberInt": "10"}, "orderStatus": "REJECTED", "seller": {"$binary": {"base64": "oUz2Lh6pQqS+DAqxRmWGeg==", "subType": "03"}}}, {"buyer": {"$binary": {"base64": "TTjV1FQfRC2X02CcmOLAEw==", "subType": "03"}}, "_id": {"$binary": {"base64": "fMR/hmF2RcWXzFy4frIftw==", "subType": "03"}}, "_class": "org.example.persistence.collections.PurchaseOrder", "uri": "903fbb9d-49a1-4e91-9eda-4220513ab5fe.pdf", "items": [{"description": "semiotics", "quantity": {"$numberInt": "15"}, "price": {"$numberDouble": "24.72645312199886"}}], "version": {"$numberInt": "4"}, "orderStatus": "CREATED", "seller": {"$binary": {"base64": "C3lhIMIrQUmy+g890u3ISg==", "subType": "03"}}}, {"buyer": {"$binary": {"base64": "Awsl+Gd1RC2MFkRvB0X2ig==", "subType": "03"}}, "_id": {"$binary": {"base64": "rmcsvND8T06s+tLnYiCA+g==", "subType": "03"}}, "_class": "org.example.persistence.collections.PurchaseOrder", "uri": "6343ec91-b3f5-4ede-bd77-f45bc34c7a57.pdf", "items": [{"description": "fanny pack", "quantity": {"$numberInt": "5"}, "price": {"$numberDouble": "15.603973289456842"}}, {"description": "fixie", "quantity": {"$numberInt": "20"}, "price": {"$numberDouble": "46.997652491215625"}}], "version": {"$numberInt": "9"}, "orderStatus": "SAVED", "seller": {"$binary": {"base64": "t5i7+z+vT92i43PtUo0dgw==", "subType": "03"}}}]